LICENSE
README.md
setup.py
tap_bing_ads/__init__.py
tap_bing_ads/exclusions.py
tap_bing_ads/reports.py
tap_bing_ads.egg-info/PKG-INFO
tap_bing_ads.egg-info/SOURCES.txt
tap_bing_ads.egg-info/dependency_links.txt
tap_bing_ads.egg-info/entry_points.txt
tap_bing_ads.egg-info/requires.txt
tap_bing_ads.egg-info/top_level.txt
tests/test_all_fields.py
tests/test_automatic_fields.py
tests/test_bookmarks.py
tests/test_bookmarks_reports.py
tests/test_discovery.py
tests/test_start_date.py
tests/test_sync_rows.py