Metadata-Version: 2.1
Name: tap-bing-ads
Version: 2.3.1
Summary: Singer.io tap for extracting data from the Bing Ads API
Home-page: http://singer.io
Author: Stitch
License: UNKNOWN
Platform: UNKNOWN
Classifier: Programming Language :: Python :: 3 :: Only
Provides-Extra: test
Provides-Extra: dev
License-File: LICENSE
